nameBinaryGenderMap/__init__.py
nameBinaryGenderMap/whats_the_gender.py
nameBinaryGenderMap-1.0.1.dist-info/METADATA
nameBinaryGenderMap-1.0.1.dist-info/WHEEL
nameBinaryGenderMap-1.0.1.dist-info/top_level.txt
nameBinaryGenderMap-1.0.1.dist-info/RECORD
