Metadata-Version: 2.1
Name: nameBinaryGenderMap
Version: 1.0.1
Summary: Get the corresponding binary gender class (i.e., male or female) for an input name.
Home-page: https://github.com/soheilesm/nameBinaryGenderMap
Author: Soheil Esmaeilzadeh
Author-email: soes@alumni.stanford.edu
License: MIT
Project-URL: Documentation, https://github.com/soheilesm/nameBinaryGenderMap/blob/main/README.md
Project-URL: Source, https://github.com/soheilesm/nameBinaryGenderMap
Project-URL: Tracker, https://github.com/soheilesm/nameBinaryGenderMap/issues
Platform: UNKNOWN
